afs_file_validator-1.1.4.dist-info/METADATA
afs_file_validator-1.1.4.dist-info/WHEEL
afs_file_validator-1.1.4.dist-info/entry_points.txt
afs_file_validator/__init__.py
afs_file_validator/fv/__init__.py
afs_file_validator/fv/files.py
afs_file_validator/fv/runner.py
afs_file_validator/fv/tools/sigcheck.exe
afs_file_validator-1.1.4.dist-info/RECORD
